<?xml version="1.0" encoding="utf-8"?>
<LanguageData>
  <!--The following translations were generated by https://www.deepl.com/-->
  <!-- EN: stuffed arctic fox -->
  <TaxidermyFox_Arctic.label>renard arctique empaillé</TaxidermyFox_Arctic.label>
  <!-- EN: A stuffed arctic fox. -->
  <TaxidermyFox_Arctic.description>Un renard arctique empaillé.</TaxidermyFox_Arctic.description>
  <TaxidermyFox_ArcticCorpse.label>renard arctique empaillé</TaxidermyFox_ArcticCorpse.label>
  <TaxidermyFox_ArcticCorpse.description>Un renard arctique empaillé.</TaxidermyFox_ArcticCorpse.description>
  <!-- EN: stuffed fennec fox -->
  <TaxidermyFox_Fennec.label>renard fennec empaillé</TaxidermyFox_Fennec.label>
  <!-- EN: A stuffed fennec fox. -->
  <TaxidermyFox_Fennec.description>Un renard fennec empaillé.</TaxidermyFox_Fennec.description>
  <TaxidermyFox_FennecCorpse.label>renard fennec empaillé</TaxidermyFox_FennecCorpse.label>
  <TaxidermyFox_FennecCorpse.description>Un renard fennec empaillé.</TaxidermyFox_FennecCorpse.description>
  <!-- EN: stuffed red fox -->
  <TaxidermyFox_Red.label>renard roux empaillé</TaxidermyFox_Red.label>
  <!-- EN: A stuffed red fox. -->
  <TaxidermyFox_Red.description>Un renard roux empaillé.</TaxidermyFox_Red.description>
  <TaxidermyFox_RedCorpse.label>renard roux empaillé</TaxidermyFox_RedCorpse.label>
  <TaxidermyFox_RedCorpse.description>Un renard roux empaillé.</TaxidermyFox_RedCorpse.description>
  <!-- EN: stuffed arctic wolf -->
  <TaxidermyWolf_Arctic.label>loup arctique empaillé</TaxidermyWolf_Arctic.label>
  <!-- EN: A stuffed arctic wolf. -->
  <TaxidermyWolf_Arctic.description>Un loup arctique empaillé.</TaxidermyWolf_Arctic.description>
  <TaxidermyWolf_ArcticCorpse.label>loup arctique empaillé</TaxidermyWolf_ArcticCorpse.label>
  <TaxidermyWolf_ArcticCorpse.description>Un loup arctique empaillé.</TaxidermyWolf_ArcticCorpse.description>
  <!-- EN: stuffed timber wolf -->
  <TaxidermyWolf_Timber.label>loup des bois empaillé</TaxidermyWolf_Timber.label>
  <!-- EN: A stuffed timber wolf. -->
  <TaxidermyWolf_Timber.description>Un loup empaillé.</TaxidermyWolf_Timber.description>
  <TaxidermyWolf_TimberCorpse.label>loup des bois empaillé</TaxidermyWolf_TimberCorpse.label>
  <TaxidermyWolf_TimberCorpse.description>Un loup empaillé.</TaxidermyWolf_TimberCorpse.description>
</LanguageData>
