<?xml version="1.0" encoding="utf-8"?>
<LanguageData>
  <!--The following translations were generated by https://www.deepl.com/-->
  <!-- EN: stuffed alpaca -->
  <TaxidermyAlpaca.label>ausgestopftes Alpaka</TaxidermyAlpaca.label>
  <!-- EN: A stuffed alpaca. -->
  <TaxidermyAlpaca.description>Ein ausgestopftes Alpaka.</TaxidermyAlpaca.description>
  <TaxidermyAlpacaCorpse.label>ausgestopftes Alpaka</TaxidermyAlpacaCorpse.label>
  <TaxidermyAlpacaCorpse.description>Ein ausgestopftes Alpaka.</TaxidermyAlpacaCorpse.description>
  <!-- EN: stuffed capybara -->
  <TaxidermyCapybara.label>ausgestopftes Wasserschwein</TaxidermyCapybara.label>
  <!-- EN: A stuffed capybara. -->
  <TaxidermyCapybara.description>Ein ausgestopftes Wasserschwein.</TaxidermyCapybara.description>
  <TaxidermyCapybaraCorpse.label>ausgestopftes Wasserschwein</TaxidermyCapybaraCorpse.label>
  <TaxidermyCapybaraCorpse.description>Ein ausgestopftes Wasserschwein.</TaxidermyCapybaraCorpse.description>
  <!-- EN: stuffed megasloth -->
  <TaxidermyMegasloth.label>ausgestopftes Megasloth</TaxidermyMegasloth.label>
  <!-- EN: A stuffed megasloth. -->
  <TaxidermyMegasloth.description>Ein ausgestopftes Megasloth.</TaxidermyMegasloth.description>
  <TaxidermyMegaslothCorpse.label>ausgestopftes Megasloth</TaxidermyMegaslothCorpse.label>
  <TaxidermyMegaslothCorpse.description>Ein ausgestopftes Megasloth.</TaxidermyMegaslothCorpse.description>
  <!-- EN: stuffed sheep -->
  <TaxidermySheep.label>ausgestopfte Schafe</TaxidermySheep.label>
  <!-- EN: A stuffed sheep. -->
  <TaxidermySheep.description>Ein ausgestopftes Schaf.</TaxidermySheep.description>
  <TaxidermySheepCorpse.label>ausgestopfte Schafe</TaxidermySheepCorpse.label>
  <TaxidermySheepCorpse.description>Ein ausgestopftes Schaf.</TaxidermySheepCorpse.description>
</LanguageData>
