<?xml version="1.0" encoding="utf-8"?>
<LanguageData>
  <!--The following translations were generated by https://www.deepl.com/-->
  <!-- EN: stuffed arctic fox -->
  <TaxidermyFox_Arctic.label>ausgestopfter Polarfuchs</TaxidermyFox_Arctic.label>
  <!-- EN: A stuffed arctic fox. -->
  <TaxidermyFox_Arctic.description>Ein ausgestopfter Polarfuchs.</TaxidermyFox_Arctic.description>
  <TaxidermyFox_ArcticCorpse.label>ausgestopfter Polarfuchs</TaxidermyFox_ArcticCorpse.label>
  <TaxidermyFox_ArcticCorpse.description>Ein ausgestopfter Polarfuchs.</TaxidermyFox_ArcticCorpse.description>
  <!-- EN: stuffed fennec fox -->
  <TaxidermyFox_Fennec.label>ausgestopfter Fennec-Fuchs</TaxidermyFox_Fennec.label>
  <!-- EN: A stuffed fennec fox. -->
  <TaxidermyFox_Fennec.description>Ein ausgestopfter Fennec-Fuchs.</TaxidermyFox_Fennec.description>
  <TaxidermyFox_FennecCorpse.label>ausgestopfter Fennec-Fuchs</TaxidermyFox_FennecCorpse.label>
  <TaxidermyFox_FennecCorpse.description>Ein ausgestopfter Fennec-Fuchs.</TaxidermyFox_FennecCorpse.description>
  <!-- EN: stuffed red fox -->
  <TaxidermyFox_Red.label>ausgestopfter Rotfuchs</TaxidermyFox_Red.label>
  <!-- EN: A stuffed red fox. -->
  <TaxidermyFox_Red.description>Ein ausgestopfter Rotfuchs.</TaxidermyFox_Red.description>
  <TaxidermyFox_RedCorpse.label>ausgestopfter Rotfuchs</TaxidermyFox_RedCorpse.label>
  <TaxidermyFox_RedCorpse.description>Ein ausgestopfter Rotfuchs.</TaxidermyFox_RedCorpse.description>
  <!-- EN: stuffed arctic wolf -->
  <TaxidermyWolf_Arctic.label>ausgestopfter arktischer wolf</TaxidermyWolf_Arctic.label>
  <!-- EN: A stuffed arctic wolf. -->
  <TaxidermyWolf_Arctic.description>Ein ausgestopfter arktischer Wolf.</TaxidermyWolf_Arctic.description>
  <TaxidermyWolf_ArcticCorpse.label>ausgestopfter arktischer wolf</TaxidermyWolf_ArcticCorpse.label>
  <TaxidermyWolf_ArcticCorpse.description>Ein ausgestopfter arktischer Wolf.</TaxidermyWolf_ArcticCorpse.description>
  <!-- EN: stuffed timber wolf -->
  <TaxidermyWolf_Timber.label>ausgestopfter Waldwolf</TaxidermyWolf_Timber.label>
  <!-- EN: A stuffed timber wolf. -->
  <TaxidermyWolf_Timber.description>Ein ausgestopfter Waldwolf.</TaxidermyWolf_Timber.description>
  <TaxidermyWolf_TimberCorpse.label>ausgestopfter Waldwolf</TaxidermyWolf_TimberCorpse.label>
  <TaxidermyWolf_TimberCorpse.description>Ein ausgestopfter Waldwolf.</TaxidermyWolf_TimberCorpse.description>
</LanguageData>
